datasette_codespaces/__init__.py
datasette_codespaces-0.1.1.dist-info/LICENSE
datasette_codespaces-0.1.1.dist-info/METADATA
datasette_codespaces-0.1.1.dist-info/WHEEL
datasette_codespaces-0.1.1.dist-info/entry_points.txt
datasette_codespaces-0.1.1.dist-info/top_level.txt
datasette_codespaces-0.1.1.dist-info/RECORD
