Metadata-Version: 2.1
Name: datasette-codespaces
Version: 0.1.1
Summary: Conveniences for running Datasette on GitHub Codespaces
Home-page: https://github.com/simonw/datasette-codespaces
Author: Simon Willison
License: Apache License, Version 2.0
Project-URL: Issues, https://github.com/simonw/datasette-codespaces/issues
Project-URL: CI, https://github.com/simonw/datasette-codespaces/actions
Project-URL: Changelog, https://github.com/simonw/datasette-codespaces/releases
Classifier: Framework :: Datasette
Classifier: License :: OSI Approved :: Apache Software License
Requires-Python: >=3.7
License-File: LICENSE
Requires-Dist: datasette
Requires-Dist: datasette-x-forwarded-host
Provides-Extra: test
Requires-Dist: pytest ; extra == 'test'
Requires-Dist: pytest-asyncio ; extra == 'test'
